Workbook

Sheet Summary
A1: DCF VALUATION | PORTFOLIO MODEL
A3: Illustrative company — five-year FCFF valuation with WACC and terminal growth sensitivity
A5: Valuation Snapshot
A7: WACC | C7: Terminal Growth | E7: Enterprise Value (€m) | G7: Implied Value / Share
A8: =Drivers!B24 -> 0.083625 | C8: =Drivers!B25 -> 0.025 | E8: =Valuation!B19 -> 3231.4096 | G8: =Valuation!B25 -> 30.314096
A9: Equity Value (€m) | C9: Net Debt (€m) | E9: 2030E FCFF (€m) | G9: Model Status
A10: =Valuation!B23 -> 3031.4096 | C10: =Drivers!B30 -> 200 | E10: =Forecast!G20 -> 219.33484 | G10: =Valuation!B27 -> OK
A13: Five-Year Free Cash Flow Profile
A15: Metric | B15: 2026E | C15: 2027E | D15: 2028E | E15: 2029E | F15: 2030E
A16: FCFF (€m) | B16: =Forecast!C20 -> 124.2 | C16: =Forecast!D20 -> 147.7685 | D16: =Forecast!E20 -> 171.6968 | E16: =Forecast!F20 -> 196.69187 | F16: =Forecast!G20 -> 219.33484
A33: Model Notes
A34: Purpose | B34: Educational / portfolio DCF model
A35: Method | B35: FCFF discounted at WACC + Gordon Growth terminal value
A36: Convention | B36: Year-end discounting
A37: Disclaimer | B37: All historical data and valuation assumptions are fictional.

Sheet Historical
A1: Historical Financials (€m)
A2: Three-year operating history used as the base for the forecast.
A4: Metric | B4: 2023A | C4: 2024A | D4: 2025A
A5: Revenue | B5: 800 | C5: 880 | D5: 1000
A6: Revenue Growth % | C6: =C5/B5-1 -> 0.1 | D6: =D5/C5-1 -> 0.13636364
A7: COGS | B7: 480 | C7: 520 | D7: 580
A8: Gross Profit | B8: =B5-B7 -> 320 | C8: =C5-C7 -> 360 | D8: =D5-D7 -> 420
A9: Gross Margin % | B9: =B8/B5 -> 0.4 | C9: =C8/C5 -> 0.40909091 | D9: =D8/D5 -> 0.42
A10: OPEX | B10: 200 | C10: 220 | D10: 250
A11: EBIT | B11: =B8-B10 -> 120 | C11: =C8-C10 -> 140 | D11: =D8-D10 -> 170
A12: EBIT Margin % | B12: =B11/B5 -> 0.15 | C12: =C11/C5 -> 0.15909091 | D12: =D11/D5 -> 0.17
A13: D&A | B13: 35 | C13: 38 | D13: 42
A14: CapEx | B14: 45 | C14: 50 | D14: 55
A15: NWC | B15: 80 | C15: 88 | D15: 100

Sheet Drivers
A1: Forecast Drivers & Valuation Assumptions
A2: Yellow cells are editable assumptions. Blue font = hardcoded input.
A4: Operating Drivers
A5: Metric | B5: 2026E | C5: 2027E | D5: 2028E | E5: 2029E | F5: 2030E
A6: Revenue Growth % | B6: 0.1 | C6: 0.09 | D6: 0.08 | E6: 0.07 | F6: 0.06
A7: COGS % of Revenue | B7: 0.575 | C7: 0.57 | D7: 0.565 | E7: 0.56 | F7: 0.555
A8: OPEX % of Revenue | B8: 0.245 | C8: 0.24 | D8: 0.235 | E8: 0.23 | F8: 0.225
A9: D&A % of Revenue | B9: 0.042 | C9: 0.042 | D9: 0.041 | E9: 0.041 | F9: 0.04
A10: CapEx % of Revenue | B10: 0.055 | C10: 0.053 | D10: 0.051 | E10: 0.05 | F10: 0.05
A11: NWC % of Revenue | B11: 0.1 | C11: 0.1 | D11: 0.1 | E11: 0.1 | F11: 0.1
A12: Tax Rate | B12: 0.25 | C12: 0.25 | D12: 0.25 | E12: 0.25 | F12: 0.25
A15: WACC & Capital Structure
A16: Metric | B16: Value
A17: Risk-free Rate | B17: 0.03
A18: Equity Risk Premium | B18: 0.06
A19: Beta | B19: 1.15
A20: Cost of Equity | B20: =B17+B18*B19 -> 0.099
A21: Pre-tax Cost of Debt | B21: 0.05
A22: Tax Rate | B22: 0.25
A23: After-tax Cost of Debt | B23: =B21*(1-B22) -> 0.0375
A24: WACC | B24: =B20*(B28/(B27+B28))+B23*(B27/(B27+B28)) -> 0.083625
A25: Terminal Growth Rate | B25: 0.025
A26: Cash (€m) | B26: 100
A27: Debt (€m) | B27: 300
A28: Equity Value for WACC (€m) | B28: 900
A29: Shares Outstanding (m) | B29: 100
A30: Net Debt (€m) | B30: =B27-B26 -> 200
A33: Model Controls
A34: Check | B34: Status
A35: WACC > Terminal Growth | B35: =IF(B24>B25,"OK","ERROR") -> OK
A36: Debt and equity weights valid | B36: =IF(AND(B27>=0,B28>0),"OK","ERROR") -> OK

Sheet Forecast
A1: Operating Forecast & FCFF (€m)
A2: Forecast linked to Drivers; FCFF = NOPAT + D&A − CapEx − Change in NWC.
A4: Metric | B4: 2025A | C4: 2026E | D4: 2027E | E4: 2028E | F4: 2029E | G4: 2030E
A5: Revenue | B5: =Historical!D5 -> 1000 | C5: =B5*(1+Drivers!B6) -> 1100 | D5: =C5*(1+Drivers!C6) -> 1199 | E5: =D5*(1+Drivers!D6) -> 1294.92 | F5: =E5*(1+Drivers!E6) -> 1385.5644 | G5: =F5*(1+Drivers!F6) -> 1468.6983
A6: Revenue Growth % | B6: =Historical!D6 -> 0.13636364 | C6: =Drivers!B6 -> 0.1 | D6: =Drivers!C6 -> 0.09 | E6: =Drivers!D6 -> 0.08 | F6: =Drivers!E6 -> 0.07 | G6: =Drivers!F6 -> 0.06
A7: COGS | B7: =Historical!D7 -> 580 | C7: =C5*Drivers!B7 -> 632.5 | D7: =D5*Drivers!C7 -> 683.43 | E7: =E5*Drivers!D7 -> 731.6298 | F7: =F5*Drivers!E7 -> 775.91606 | G7: =G5*Drivers!F7 -> 815.12754
A8: Gross Profit | B8: =Historical!D8 -> 420 | C8: =C5-C7 -> 467.5 | D8: =D5-D7 -> 515.57 | E8: =E5-E7 -> 563.2902 | F8: =F5-F7 -> 609.64834 | G8: =G5-G7 -> 653.57073
A9: Gross Margin % | B9: =Historical!D9 -> 0.42 | C9: =C8/C5 -> 0.425 | D9: =D8/D5 -> 0.43 | E9: =E8/E5 -> 0.435 | F9: =F8/F5 -> 0.44 | G9: =G8/G5 -> 0.445
A10: OPEX | B10: =Historical!D10 -> 250 | C10: =C5*Drivers!B8 -> 269.5 | D10: =D5*Drivers!C8 -> 287.76 | E10: =E5*Drivers!D8 -> 304.3062 | F10: =F5*Drivers!E8 -> 318.67981 | G10: =G5*Drivers!F8 -> 330.45711
A11: EBIT | B11: =Historical!D11 -> 170 | C11: =C8-C10 -> 198 | D11: =D8-D10 -> 227.81 | E11: =E8-E10 -> 258.984 | F11: =F8-F10 -> 290.96852 | G11: =G8-G10 -> 323.11362
A12: EBIT Margin % | B12: =Historical!D12 -> 0.17 | C12: =C11/C5 -> 0.18 | D12: =D11/D5 -> 0.19 | E12: =E11/E5 -> 0.2 | F12: =F11/F5 -> 0.21 | G12: =G11/G5 -> 0.22
A13: Tax Rate | C13: =Drivers!B12 -> 0.25 | D13: =Drivers!C12 -> 0.25 | E13: =Drivers!D12 -> 0.25 | F13: =Drivers!E12 -> 0.25 | G13: =Drivers!F12 -> 0.25
A14: Cash Taxes | C14: =C11*C13 -> 49.5 | D14: =D11*D13 -> 56.9525 | E14: =E11*E13 -> 64.746 | F14: =F11*F13 -> 72.742131 | G14: =G11*G13 -> 80.778405
A15: NOPAT | C15: =C11-C14 -> 148.5 | D15: =D11-D14 -> 170.8575 | E15: =E11-E14 -> 194.238 | F15: =F11-F14 -> 218.22639 | G15: =G11-G14 -> 242.33521
A16: D&A | B16: =Historical!D13 -> 42 | C16: =C5*Drivers!B9 -> 46.2 | D16: =D5*Drivers!C9 -> 50.358 | E16: =E5*Drivers!D9 -> 53.09172 | F16: =F5*Drivers!E9 -> 56.80814 | G16: =G5*Drivers!F9 -> 58.747931
A17: CapEx | B17: =Historical!D14 -> 55 | C17: =C5*Drivers!B10 -> 60.5 | D17: =D5*Drivers!C10 -> 63.547 | E17: =E5*Drivers!D10 -> 66.04092 | F17: =F5*Drivers!E10 -> 69.27822 | G17: =G5*Drivers!F10 -> 73.434913
A18: NWC | B18: =Historical!D15 -> 100 | C18: =C5*Drivers!B11 -> 110 | D18: =D5*Drivers!C11 -> 119.9 | E18: =E5*Drivers!D11 -> 129.492 | F18: =F5*Drivers!E11 -> 138.55644 | G18: =G5*Drivers!F11 -> 146.86983
A19: Change in NWC | C19: =C18-B18 -> 10 | D19: =D18-C18 -> 9.9 | E19: =E18-D18 -> 9.592 | F19: =F18-E18 -> 9.06444 | G19: =G18-F18 -> 8.3133864
A20: FCFF | C20: =C15+C16-C17-C19 -> 124.2 | D20: =D15+D16-D17-D19 -> 147.7685 | E20: =E15+E16-E17-E19 -> 171.6968 | F20: =F15+F16-F17-F19 -> 196.69187 | G20: =G15+G16-G17-G19 -> 219.33484

Sheet Valuation
A1: DCF Valuation (€m, except per-share data)
A2: Year-end discounting convention | Gordon Growth terminal value
A4: Present Value of Forecast Cash Flows
A5: Metric | B5: 2026E | C5: 2027E | D5: 2028E | E5: 2029E | F5: 2030E
A6: FCFF | B6: =Forecast!C20 -> 124.2 | C6: =Forecast!D20 -> 147.7685 | D6: =Forecast!E20 -> 171.6968 | E6: =Forecast!F20 -> 196.69187 | F6: =Forecast!G20 -> 219.33484
A7: Discount Period | B7: 1 | C7: 2 | D7: 3 | E7: 4 | F7: 5
A8: Discount Factor | B8: =1/(1+Drivers!$B$24)^B7 -> 0.92282847 | C8: =1/(1+Drivers!$B$24)^C7 -> 0.85161238 | D8: =1/(1+Drivers!$B$24)^D7 -> 0.78589215 | E8: =1/(1+Drivers!$B$24)^E7 -> 0.72524365 | F8: =1/(1+Drivers!$B$24)^F7 -> 0.66927549
A9: PV of FCFF | B9: =B6*B8 -> 114.6153 | C9: =C6*C8 -> 125.84148 | D9: =D6*D8 -> 134.93517 | E9: =E6*E8 -> 142.64953 | F9: =F6*F8 -> 146.79544
A11: Terminal Value
A12: Terminal Growth Rate | B12: =Drivers!B25 -> 0.025
A13: WACC | B13: =Drivers!B24 -> 0.083625
A14: Terminal FCFF | B14: =F6*(1+B12) -> 224.81822
A15: Terminal Value | B15: =B14/(B13-B12) -> 3834.8523
A16: PV of Terminal Value | B16: =B15*F8 -> 2566.5726
A18: Equity Bridge
A19: Enterprise Value | B19: =SUM(B9:F9)+B16 -> 3231.4096
A20: Less: Debt | B20: =Drivers!B27 -> 300
A21: Add: Cash | B21: =Drivers!B26 -> 100
A22: Net Debt | B22: =B20-B21 -> 200
A23: Equity Value | B23: =B19-B22 -> 3031.4096
A24: Shares Outstanding (m) | B24: =Drivers!B29 -> 100
A25: Implied Value / Share | B25: =B23/B24 -> 30.314096
A26: Terminal Value / Enterprise Value | B26: =B16/B19 -> 0.79425792
A27: Model Status | B27: =IF(AND(B13>B12,B19>0,B23>0,B25>0),"OK","ERROR") -> OK

Sheet Sensitivity
A1: Sensitivity Analysis — Implied Value / Share (€)
A2: Base case centered in the table: WACC ±1.0% and terminal growth ±1.0%.
A4: Base WACC | B4: =Drivers!B24 -> 0.083625
A5: Base Terminal Growth | B5: =Drivers!B25 -> 0.025
B7: TGR \ WACC | C7: =$B$4-0.01 -> 0.073625 | D7: =$B$4-0.005 -> 0.078625 | E7: =$B$4 -> 0.083625 | F7: =$B$4+0.005 -> 0.088625 | G7: =$B$4+0.01 -> 0.093625
B8: =$B$5-0.01 -> 0.015 | C8: =((Forecast!$C$20/(1+C$7)^1)+(Forecast!$D$20/(1+C$7)^2)+(Forecast!$E$20/(1+C$7)^3)+(Forecast!$F$20/(1+C$7)^4)+(Forecast!$G$20/(1+C$7)^5)+(((Forecast!$G$20*(1+$B8))/(C$7-$B8))/(1+C$7)^5)-Drivers!$B$27+Drivers!$B$26)/Drivers!$B$29 -> 31.465404 | D8: =((Forecast!$C$20/(1+D$7)^1)+(Forecast!$D$20/(1+D$7)^2)+(Forecast!$E$20/(1+D$7)^3)+(Forecast!$F$20/(1+D$7)^4)+(Forecast!$G$20/(1+D$7)^5)+(((Forecast!$G$20*(1+$B8))/(D$7-$B8))/(1+D$7)^5)-Drivers!$B$27+Drivers!$B$26)/Drivers!$B$29 -> 28.711088 | E8: =((Forecast!$C$20/(1+E$7)^1)+(Forecast!$D$20/(1+E$7)^2)+(Forecast!$E$20/(1+E$7)^3)+(Forecast!$F$20/(1+E$7)^4)+(Forecast!$G$20/(1+E$7)^5)+(((Forecast!$G$20*(1+$B8))/(E$7-$B8))/(1+E$7)^5)-Drivers!$B$27+Drivers!$B$26)/Drivers!$B$29 -> 26.360189 | F8: =((Forecast!$C$20/(1+F$7)^1)+(Forecast!$D$20/(1+F$7)^2)+(Forecast!$E$20/(1+F$7)^3)+(Forecast!$F$20/(1+F$7)^4)+(Forecast!$G$20/(1+F$7)^5)+(((Forecast!$G$20*(1+$B8))/(F$7-$B8))/(1+F$7)^5)-Drivers!$B$27+Drivers!$B$26)/Drivers!$B$29 -> 24.330472 | G8: =((Forecast!$C$20/(1+G$7)^1)+(Forecast!$D$20/(1+G$7)^2)+(Forecast!$E$20/(1+G$7)^3)+(Forecast!$F$20/(1+G$7)^4)+(Forecast!$G$20/(1+G$7)^5)+(((Forecast!$G$20*(1+$B8))/(G$7-$B8))/(1+G$7)^5)-Drivers!$B$27+Drivers!$B$26)/Drivers!$B$29 -> 22.56062
B9: =$B$5-0.005 -> 0.02 | C9: =((Forecast!$C$20/(1+C$7)^1)+(Forecast!$D$20/(1+C$7)^2)+(Forecast!$E$20/(1+C$7)^3)+(Forecast!$F$20/(1+C$7)^4)+(Forecast!$G$20/(1+C$7)^5)+(((Forecast!$G$20*(1+$B9))/(C$7-$B9))/(1+C$7)^5)-Drivers!$B$27+Drivers!$B$26)/Drivers!$B$29 -> 34.090934 | D9: =((Forecast!$C$20/(1+D$7)^1)+(Forecast!$D$20/(1+D$7)^2)+(Forecast!$E$20/(1+D$7)^3)+(Forecast!$F$20/(1+D$7)^4)+(Forecast!$G$20/(1+D$7)^5)+(((Forecast!$G$20*(1+$B9))/(D$7-$B9))/(1+D$7)^5)-Drivers!$B$27+Drivers!$B$26)/Drivers!$B$29 -> 30.883215 | E9: =((Forecast!$C$20/(1+E$7)^1)+(Forecast!$D$20/(1+E$7)^2)+(Forecast!$E$20/(1+E$7)^3)+(Forecast!$F$20/(1+E$7)^4)+(Forecast!$G$20/(1+E$7)^5)+(((Forecast!$G$20*(1+$B9))/(E$7-$B9))/(1+E$7)^5)-Drivers!$B$27+Drivers!$B$26)/Drivers!$B$29 -> 28.181783 | F9: =((Forecast!$C$20/(1+F$7)^1)+(Forecast!$D$20/(1+F$7)^2)+(Forecast!$E$20/(1+F$7)^3)+(Forecast!$F$20/(1+F$7)^4)+(Forecast!$G$20/(1+F$7)^5)+(((Forecast!$G$20*(1+$B9))/(F$7-$B9))/(1+F$7)^5)-Drivers!$B$27+Drivers!$B$26)/Drivers!$B$29 -> 25.875928 | G9: =((Forecast!$C$20/(1+G$7)^1)+(Forecast!$D$20/(1+G$7)^2)+(Forecast!$E$20/(1+G$7)^3)+(Forecast!$F$20/(1+G$7)^4)+(Forecast!$G$20/(1+G$7)^5)+(((Forecast!$G$20*(1+$B9))/(G$7-$B9))/(1+G$7)^5)-Drivers!$B$27+Drivers!$B$26)/Drivers!$B$29 -> 23.885016
B10: =$B$5 -> 0.025 | C10: =((Forecast!$C$20/(1+C$7)^1)+(Forecast!$D$20/(1+C$7)^2)+(Forecast!$E$20/(1+C$7)^3)+(Forecast!$F$20/(1+C$7)^4)+(Forecast!$G$20/(1+C$7)^5)+(((Forecast!$G$20*(1+$B10))/(C$7-$B10))/(1+C$7)^5)-Drivers!$B$27+Drivers!$B$26)/Drivers!$B$29 -> 37.256419 | D10: =((Forecast!$C$20/(1+D$7)^1)+(Forecast!$D$20/(1+D$7)^2)+(Forecast!$E$20/(1+D$7)^3)+(Forecast!$F$20/(1+D$7)^4)+(Forecast!$G$20/(1+D$7)^5)+(((Forecast!$G$20*(1+$B10))/(D$7-$B10))/(1+D$7)^5)-Drivers!$B$27+Drivers!$B$26)/Drivers!$B$29 -> 33.460399 | E10: =((Forecast!$C$20/(1+E$7)^1)+(Forecast!$D$20/(1+E$7)^2)+(Forecast!$E$20/(1+E$7)^3)+(Forecast!$F$20/(1+E$7)^4)+(Forecast!$G$20/(1+E$7)^5)+(((Forecast!$G$20*(1+$B10))/(E$7-$B10))/(1+E$7)^5)-Drivers!$B$27+Drivers!$B$26)/Drivers!$B$29 -> 30.314096 | F10: =((Forecast!$C$20/(1+F$7)^1)+(Forecast!$D$20/(1+F$7)^2)+(Forecast!$E$20/(1+F$7)^3)+(Forecast!$F$20/(1+F$7)^4)+(Forecast!$G$20/(1+F$7)^5)+(((Forecast!$G$20*(1+$B10))/(F$7-$B10))/(1+F$7)^5)-Drivers!$B$27+Drivers!$B$26)/Drivers!$B$29 -> 27.664286 | G10: =((Forecast!$C$20/(1+G$7)^1)+(Forecast!$D$20/(1+G$7)^2)+(Forecast!$E$20/(1+G$7)^3)+(Forecast!$F$20/(1+G$7)^4)+(Forecast!$G$20/(1+G$7)^5)+(((Forecast!$G$20*(1+$B10))/(G$7-$B10))/(1+G$7)^5)-Drivers!$B$27+Drivers!$B$26)/Drivers!$B$29 -> 25.402403
B11: =$B$5+0.005 -> 0.03 | C11: =((Forecast!$C$20/(1+C$7)^1)+(Forecast!$D$20/(1+C$7)^2)+(Forecast!$E$20/(1+C$7)^3)+(Forecast!$F$20/(1+C$7)^4)+(Forecast!$G$20/(1+C$7)^5)+(((Forecast!$G$20*(1+$B11))/(C$7-$B11))/(1+C$7)^5)-Drivers!$B$27+Drivers!$B$26)/Drivers!$B$29 -> 41.147516 | D11: =((Forecast!$C$20/(1+D$7)^1)+(Forecast!$D$20/(1+D$7)^2)+(Forecast!$E$20/(1+D$7)^3)+(Forecast!$F$20/(1+D$7)^4)+(Forecast!$G$20/(1+D$7)^5)+(((Forecast!$G$20*(1+$B11))/(D$7-$B11))/(1+D$7)^5)-Drivers!$B$27+Drivers!$B$26)/Drivers!$B$29 -> 36.567596 | E11: =((Forecast!$C$20/(1+E$7)^1)+(Forecast!$D$20/(1+E$7)^2)+(Forecast!$E$20/(1+E$7)^3)+(Forecast!$F$20/(1+E$7)^4)+(Forecast!$G$20/(1+E$7)^5)+(((Forecast!$G$20*(1+$B11))/(E$7-$B11))/(1+E$7)^5)-Drivers!$B$27+Drivers!$B$26)/Drivers!$B$29 -> 32.844043 | F11: =((Forecast!$C$20/(1+F$7)^1)+(Forecast!$D$20/(1+F$7)^2)+(Forecast!$E$20/(1+F$7)^3)+(Forecast!$F$20/(1+F$7)^4)+(Forecast!$G$20/(1+F$7)^5)+(((Forecast!$G$20*(1+$B11))/(F$7-$B11))/(1+F$7)^5)-Drivers!$B$27+Drivers!$B$26)/Drivers!$B$29 -> 29.757693 | G11: =((Forecast!$C$20/(1+G$7)^1)+(Forecast!$D$20/(1+G$7)^2)+(Forecast!$E$20/(1+G$7)^3)+(Forecast!$F$20/(1+G$7)^4)+(Forecast!$G$20/(1+G$7)^5)+(((Forecast!$G$20*(1+$B11))/(G$7-$B11))/(1+G$7)^5)-Drivers!$B$27+Drivers!$B$26)/Drivers!$B$29 -> 27.158279
B12: =$B$5+0.01 -> 0.035 | C12: =((Forecast!$C$20/(1+C$7)^1)+(Forecast!$D$20/(1+C$7)^2)+(Forecast!$E$20/(1+C$7)^3)+(Forecast!$F$20/(1+C$7)^4)+(Forecast!$G$20/(1+C$7)^5)+(((Forecast!$G$20*(1+$B12))/(C$7-$B12))/(1+C$7)^5)-Drivers!$B$27+Drivers!$B$26)/Drivers!$B$29 -> 46.046018 | D12: =((Forecast!$C$20/(1+D$7)^1)+(Forecast!$D$20/(1+D$7)^2)+(Forecast!$E$20/(1+D$7)^3)+(Forecast!$F$20/(1+D$7)^4)+(Forecast!$G$20/(1+D$7)^5)+(((Forecast!$G$20*(1+$B12))/(D$7-$B12))/(1+D$7)^5)-Drivers!$B$27+Drivers!$B$26)/Drivers!$B$29 -> 40.387045 | E12: =((Forecast!$C$20/(1+E$7)^1)+(Forecast!$D$20/(1+E$7)^2)+(Forecast!$E$20/(1+E$7)^3)+(Forecast!$F$20/(1+E$7)^4)+(Forecast!$G$20/(1+E$7)^5)+(((Forecast!$G$20*(1+$B12))/(E$7-$B12))/(1+E$7)^5)-Drivers!$B$27+Drivers!$B$26)/Drivers!$B$29 -> 35.894287 | F12: =((Forecast!$C$20/(1+F$7)^1)+(Forecast!$D$20/(1+F$7)^2)+(Forecast!$E$20/(1+F$7)^3)+(Forecast!$F$20/(1+F$7)^4)+(Forecast!$G$20/(1+F$7)^5)+(((Forecast!$G$20*(1+$B12))/(F$7-$B12))/(1+F$7)^5)-Drivers!$B$27+Drivers!$B$26)/Drivers!$B$29 -> 32.24148 | G12: =((Forecast!$C$20/(1+G$7)^1)+(Forecast!$D$20/(1+G$7)^2)+(Forecast!$E$20/(1+G$7)^3)+(Forecast!$F$20/(1+G$7)^4)+(Forecast!$G$20/(1+G$7)^5)+(((Forecast!$G$20*(1+$B12))/(G$7-$B12))/(1+G$7)^5)-Drivers!$B$27+Drivers!$B$26)/Drivers!$B$29 -> 29.213664
B15: Higher WACC reduces valuation; higher terminal growth increases valuation.
